odoo/addons/ssi_general_audit_worksheet_romm/README.rst
odoo/addons/ssi_general_audit_worksheet_romm/__init__.py
odoo/addons/ssi_general_audit_worksheet_romm/__manifest__.py
odoo/addons/ssi_general_audit_worksheet_romm/data/general_audit_worksheet_type_data.xml
odoo/addons/ssi_general_audit_worksheet_romm/data/approval_template/general_audit_ws_c165170.xml
odoo/addons/ssi_general_audit_worksheet_romm/data/approval_template/general_audit_ws_d66d87a.xml
odoo/addons/ssi_general_audit_worksheet_romm/data/ir_sequence/general_audit_ws_c165170.xml
odoo/addons/ssi_general_audit_worksheet_romm/data/ir_sequence/general_audit_ws_d66d87a.xml
odoo/addons/ssi_general_audit_worksheet_romm/data/policy_template/general_audit_ws_c165170.xml
odoo/addons/ssi_general_audit_worksheet_romm/data/policy_template/general_audit_ws_d66d87a.xml
odoo/addons/ssi_general_audit_worksheet_romm/data/sequence_template/general_audit_ws_c165170.xml
odoo/addons/ssi_general_audit_worksheet_romm/data/sequence_template/general_audit_ws_d66d87a.xml
odoo/addons/ssi_general_audit_worksheet_romm/models/__init__.py
odoo/addons/ssi_general_audit_worksheet_romm/models/general_audit_standard_detail.py
odoo/addons/ssi_general_audit_worksheet_romm/models/general_audit_ws_c165170.py
odoo/addons/ssi_general_audit_worksheet_romm/models/general_audit_ws_d66d87a.py
odoo/addons/ssi_general_audit_worksheet_romm/models/general_audit_ws_d66d87a_detail.py
odoo/addons/ssi_general_audit_worksheet_romm/models/ws_ra230.py
odoo/addons/ssi_general_audit_worksheet_romm/models/ws_ra230_account_assersion_level_romm.py
odoo/addons/ssi_general_audit_worksheet_romm/security/ir_module_category_data.xml
odoo/addons/ssi_general_audit_worksheet_romm/security/ir_model_access/general_audit_ws_c165170.xml
odoo/addons/ssi_general_audit_worksheet_romm/security/ir_model_access/general_audit_ws_d66d87a.xml
odoo/addons/ssi_general_audit_worksheet_romm/security/ir_rule/general_audit_ws_c165170.xml
odoo14_addon_ssi_general_audit_worksheet_romm-14.0.1.1.0.dist-info/METADATA
odoo14_addon_ssi_general_audit_worksheet_romm-14.0.1.1.0.dist-info/WHEEL
odoo14_addon_ssi_general_audit_worksheet_romm-14.0.1.1.0.dist-info/top_level.txt
odoo14_addon_ssi_general_audit_worksheet_romm-14.0.1.1.0.dist-info/RECORD
